rrgit/__init__.py
rrgit/__main__.py
rrgit/dotconfig.py
rrgit/log.py
rrgit/symbols.py
rrgit/util.py
rrgit/version.py
rrgit/commands/__init__.py
rrgit/commands/clone.py
rrgit/commands/command.py
rrgit/commands/diff.py
rrgit/commands/file_ops.py
rrgit/commands/pull.py
rrgit/commands/push.py
rrgit/commands/status.py
rrgit/commands/watch.py
rrgit-1.0.1.dist-info/LICENSE
rrgit-1.0.1.dist-info/METADATA
rrgit-1.0.1.dist-info/WHEEL
rrgit-1.0.1.dist-info/entry_points.txt
rrgit-1.0.1.dist-info/top_level.txt
rrgit-1.0.1.dist-info/RECORD
