Metadata-Version: 2.1
Name: rrgit
Version: 1.0.1
Summary: CLI tool for syncing files to and from RepRapFirmware 3 via the web API
Home-page: https://github.com/adammhaile/rrgit
Author: Adam Haile
Author-email: adammhaile@gmail.com
License: GNU General Public License v3 (GPLv3)
Platform: UNKNOWN
Classifier: Development Status :: 4 - Beta
Classifier: Programming Language :: Python :: 3.7
Classifier: Programming Language :: Python :: 3.8
Classifier: Programming Language :: Python :: 3.9
Classifier: Environment :: Console
Classifier: License :: OSI Approved :: GNU General Public License v3 (GPLv3)
Classifier: Natural Language :: English
Requires-Dist: duetwebapi
Requires-Dist: pyyaml
Requires-Dist: colorama
Requires-Dist: pathspec
Requires-Dist: watchdog
